merrypopins/__init__.py
merrypopins/load_datasets.py
merrypopins/locate.py
merrypopins/make_dataset.py
merrypopins/preprocess.py
merrypopins/statistics.py
merrypopins-1.0.4.dist-info/licenses/LICENSE
merrypopins-1.0.4.dist-info/METADATA
merrypopins-1.0.4.dist-info/WHEEL
merrypopins-1.0.4.dist-info/top_level.txt
merrypopins-1.0.4.dist-info/RECORD
