Metadata-Version: 2.4
Name: merrypopins
Version: 1.0.4
Summary: Merrypopins: Automated pop-in detection for nano-indentation experiments tooling: load_datasets, preprocess, locate, statistics & make_dataset
Author-email: Cahit Acar <c.acar.business@gmail.com>, Anna Marcelissen <anna.marcelissen@live.nl>, Hugo van Schrojenstein Lantman <h.w.vanschrojensteinlantman@uu.nl>, "John M. Aiken" <johnm.aiken@gmail.com>
License: MIT
Project-URL: Homepage, https://serprateai.github.io/merrypopins/
Project-URL: Source, https://github.com/SerpRateAI/merrypopins
Classifier: Intended Audience :: Science/Research
Classifier: License :: OSI Approved :: MIT License
Classifier: Programming Language :: Python :: 3.10
Classifier: Programming Language :: Python :: 3.11
Classifier: Programming Language :: Python :: 3.12
Classifier: Programming Language :: Python :: 3.13
Classifier: Operating System :: OS Independent
Classifier: Topic :: Scientific/Engineering :: Physics
Requires-Python: <3.14,>=3.10
License-File: LICENSE
Requires-Dist: matplotlib>=3.7
Requires-Dist: numpy>=1.23
Requires-Dist: pandas>=2.2
Requires-Dist: scipy>=1.10
Requires-Dist: scikit-learn>=1.2
Requires-Dist: tensorflow>=2.10
Provides-Extra: dev
Requires-Dist: black>=23.0; extra == "dev"
Requires-Dist: coverage>=7.0; extra == "dev"
Requires-Dist: pre-commit>=3.0; extra == "dev"
Requires-Dist: pytest>=7.0; extra == "dev"
Requires-Dist: pytest-cov>=4.0; extra == "dev"
Requires-Dist: ruff>=0.8.0; extra == "dev"
Dynamic: license-file
